oauth2/__init__.py
oauth2/admin.py
oauth2/apps.py
oauth2/config.py
oauth2/encoder.py
oauth2/models.py
oauth2/serializers.py
oauth2/tests.py
oauth2/urls.py
oauth2/utils.py
oauth2/views.py
oauth2/migrations/0001_initial.py
oauth2/migrations/__init__.py
oauth2/services/__init__.py
oauth2/services/facebook.py
oauth2/services/github.py
oauth2/services/google.py
oauth2/services/register.py
drf_oauth2-0.3.dist-info/LICENSE
drf_oauth2-0.3.dist-info/METADATA
drf_oauth2-0.3.dist-info/WHEEL
drf_oauth2-0.3.dist-info/top_level.txt
drf_oauth2-0.3.dist-info/RECORD
